cs_kit/__init__.py
cs_kit/api.py
cs_kit/buildpacks.py
cs_kit/cli.py
cs_kit/exceptions.py
cs_kit/filespec.py
cs_kit/schemas.py
cs_kit/validate.py
cs_kit/tests/__init__.py
cs_kit/tests/test_FunctionsTest.py
cs_kit/tests/test_buildpacks.py
cs_kit/tests/test_filespec.py
cs_kit-1.16.9.dist-info/LICENSE
cs_kit-1.16.9.dist-info/METADATA
cs_kit-1.16.9.dist-info/WHEEL
cs_kit-1.16.9.dist-info/entry_points.txt
cs_kit-1.16.9.dist-info/top_level.txt
cs_kit-1.16.9.dist-info/RECORD
