Metadata-Version: 2.1
Name: cs-kit
Version: 1.16.9
Summary: Developer tools for compute.studio.
Home-page: https://github.com/compute-studio-org/Compute-Studio-Toolkit
Author: Hank Doupe
Author-email: henrymdoupe@gmail.com
License: UNKNOWN
Platform: UNKNOWN
Classifier: Programming Language :: Python :: 3
Classifier: License :: OSI Approved :: MIT License
Classifier: Operating System :: OS Independent
Requires-Dist: paramtools
Requires-Dist: cs-storage
Requires-Dist: fsspec
Requires-Dist: pyyaml
